weltschmerz/__init__.py
weltschmerz/anidb.py
weltschmerz/anime.py
weltschmerz/delete_duplicates.py
weltschmerz/filehash.py
weltschmerz/filehasher.py
weltschmerz/masks.py
weltschmerz/move_files.py
weltschmerz/pyselect.py
weltschmerz/remove_changed.py
weltschmerz/remove_deleted.py
weltschmerz/test_filehash.py
weltschmerz-1.0.1.dist-info/licenses/LICENSE.md
weltschmerz-1.0.1.dist-info/METADATA
weltschmerz-1.0.1.dist-info/WHEEL
weltschmerz-1.0.1.dist-info/entry_points.txt
weltschmerz-1.0.1.dist-info/top_level.txt
weltschmerz-1.0.1.dist-info/RECORD
