Metadata-Version: 2.4
Name: weltschmerz
Version: 1.0.1
Summary: local anime file database with deduplication and sorting
Maintainer: zerimond
Project-URL: Homepage, https://codeberg.org/zeromind/weltschmerz
Project-URL: Issues, https://codeberg.org/zeromind/weltschmerz/issues
Classifier: Development Status :: 5 - Production/Stable
Classifier: Intended Audience :: End Users/Desktop
Classifier: Programming Language :: Python :: 3
Classifier: License :: OSI Approved :: MIT License
Classifier: Operating System :: OS Independent
Requires-Python: >=3.6
License-File: LICENSE.md
Requires-Dist: SQLAlchemy
Requires-Dist: pycryptodome
Requires-Dist: click
Requires-Dist: yumemi
Dynamic: license-file
